README.md
setup.py
xmrig_auto_throttler/__init__.py
xmrig_auto_throttler/__main__.py
xmrig_auto_throttler/args.py
xmrig_auto_throttler/cmd.py
xmrig_auto_throttler/dependencies.py
xmrig_auto_throttler/idle.py
xmrig_auto_throttler/version.py
xmrig_auto_throttler/xmrig_api_client.py
xmrig_auto_throttler.egg-info/PKG-INFO
xmrig_auto_throttler.egg-info/SOURCES.txt
xmrig_auto_throttler.egg-info/dependency_links.txt
xmrig_auto_throttler.egg-info/entry_points.txt
xmrig_auto_throttler.egg-info/requires.txt
xmrig_auto_throttler.egg-info/top_level.txt