Metadata-Version: 2.1
Name: xmrig-auto-throttler
Version: 0.0.1
Summary: Program that switches between xmrig profiles according to your computer usage.
Home-page: https://github.com/dhensen/xmrig-auto-idle-throttler
Author: Dino Hensen
Author-email: dino.hensen+xmrigthrottle@gmail.com
License: UNKNOWN
Platform: UNKNOWN
Classifier: Programming Language :: Python :: 3
Classifier: License :: OSI Approved :: MIT License
Classifier: Operating System :: OS Independent
Requires-Python: >=3.6
Provides-Extra: dev
